Generic_Util/__init__.py
Generic_Util/benchmarking.py
Generic_Util/iter.py
Generic_Util/misc.py
Generic_Util/operator.py
Generic_Util/py.typed
Generic_Util/_compat/__init__.py
Generic_Util/_compat/typing.py
Generic_Util/numba/__init__.py
Generic_Util/numba/benchmarking.py
Generic_Util/numba/higher_order.py
Generic_Util/numba/types.py
generic_util-0.1.0.dist-info/METADATA
generic_util-0.1.0.dist-info/WHEEL
generic_util-0.1.0.dist-info/licenses/LICENSE
generic_util-0.1.0.dist-info/RECORD
