Metadata-Version: 2.1
Name: Generic-Util
Version: 0.1.0
Summary: A collection of frequently used (mostly functional) utilities not found in the standard library
Project-URL: Homepage, https://github.com/T-Flet/Generic-Util
Project-URL: Bug Tracker, https://github.com/T-Flet/Generic-Util/issues
Project-URL: Discussions, https://github.com/T-Flet/Generic-Util/discussions
Project-URL: Changelog, https://github.com/T-Flet/Generic-Util/releases
Author-email: Thomas Fletcher <T-Fletcher@outlook.com>
License-File: LICENSE
Classifier: Development Status :: 1 - Planning
Classifier: Intended Audience :: Developers
Classifier: License :: OSI Approved :: BSD License
Classifier: Operating System :: OS Independent
Classifier: Programming Language :: Python
Classifier: Programming Language :: Python :: 3.10
Classifier: Programming Language :: Python :: 3.11
Classifier: Typing :: Typed
Requires-Python: >=3.10
Requires-Dist: numpy>=1.23.5
Requires-Dist: pandas>=1.5.3
Requires-Dist: sortedcontainers>=2.4.0
Requires-Dist: typing-extensions>=3.7; python_version < '3.8'
Provides-Extra: dev
Requires-Dist: pytest-cov>=3; extra == 'dev'
Requires-Dist: pytest>=6; extra == 'dev'
Provides-Extra: docs
Requires-Dist: furo; extra == 'docs'
Requires-Dist: myst-parser>=0.13; extra == 'docs'
Requires-Dist: sphinx-book-theme>=0.1.0; extra == 'docs'
Requires-Dist: sphinx-copybutton; extra == 'docs'
Requires-Dist: sphinx>=4.0; extra == 'docs'
Provides-Extra: test
Requires-Dist: pytest-cov>=3; extra == 'test'
Requires-Dist: pytest>=6; extra == 'test'
